main.py
construct/__init__.py
exceptions/__init__.py
messages/__init__.py
messages/help/__init__.py
validation/__init__.py
ecv_codegen-0.0.3.dist-info/METADATA
ecv_codegen-0.0.3.dist-info/WHEEL
ecv_codegen-0.0.3.dist-info/entry_points.txt
ecv_codegen-0.0.3.dist-info/top_level.txt
ecv_codegen-0.0.3.dist-info/RECORD
